mcp_proxy_sigv4/__init__.py
mcp_proxy_sigv4/__main__.py
mcp_proxy_sigv4/cli.py
mcp_proxy_sigv4/proxy.py
mcp_proxy_sigv4/sigv4_auth.py
mcp_proxy_sigv4-0.1.2.dist-info/METADATA
mcp_proxy_sigv4-0.1.2.dist-info/WHEEL
mcp_proxy_sigv4-0.1.2.dist-info/entry_points.txt
mcp_proxy_sigv4-0.1.2.dist-info/licenses/LICENSE
mcp_proxy_sigv4-0.1.2.dist-info/RECORD
