Metadata-Version: 2.4
Name: mcp-proxy-sigv4
Version: 0.1.2
Summary: MCP proxy server with AWS SigV4 authentication and OAuth support
Author: Jiaping Zeng
License: MIT
License-File: LICENSE
Keywords: aws,mcp,oauth,proxy,sigv4
Classifier: Development Status :: 4 - Beta
Classifier: Intended Audience :: Developers
Classifier: License :: OSI Approved :: MIT License
Classifier: Programming Language :: Python :: 3
Classifier: Programming Language :: Python :: 3.10
Classifier: Programming Language :: Python :: 3.11
Classifier: Programming Language :: Python :: 3.12
Requires-Python: >=3.10
Requires-Dist: boto3>=1.26.0
Requires-Dist: click>=8.0.0
Requires-Dist: fastmcp>=2.10.0
Requires-Dist: requests-aws4auth>=1.1.0
Requires-Dist: requests>=2.28.0
Requires-Dist: urllib3>=1.26.0
Provides-Extra: dev
Requires-Dist: pytest-asyncio>=0.21.0; extra == 'dev'
Requires-Dist: pytest-mock>=3.10.0; extra == 'dev'
Requires-Dist: pytest>=7.0.0; extra == 'dev'
Requires-Dist: ruff>=0.1.0; extra == 'dev'
